Metadata-Version: 2.1
Name: cypstrate
Version: 0.1.6
Summary: CYPstrate: Prediction of Cytochrome P450 substrates
Home-page: https://github.com/molinfo-vienna/cypstrate.git
Maintainer: Johannes Kirchmair
Maintainer-email: johannes.kirchmair@univie.ac.at
Requires-Python: >=3.8,<3.9
License-File: LICENSE
Requires-Dist: rdkit >=2022.3.3
Requires-Dist: scikit-learn ==0.23.2
Requires-Dist: gensim ==3.8.3
Requires-Dist: pandas ==1.2.1
Requires-Dist: numpy ==1.19.2
Requires-Dist: mol2vec ==0.2.2
Requires-Dist: nerdd-module >=0.1.9
Requires-Dist: chembl-structure-pipeline <1.2.0,>=1.0.0
Requires-Dist: setuptools <60.0
Requires-Dist: importlib-resources >=6.1.1 ; python_version < "3.10"
Provides-Extra: dev
Requires-Dist: mypy ; extra == 'dev'
Requires-Dist: isort ; extra == 'dev'
Requires-Dist: black ; extra == 'dev'
Provides-Extra: test
Requires-Dist: pytest ; extra == 'test'
Requires-Dist: pytest-watch ; extra == 'test'
Requires-Dist: pytest-cov ; extra == 'test'
Requires-Dist: pytest-bdd ; extra == 'test'
Requires-Dist: hypothesis ; extra == 'test'
Requires-Dist: hypothesis-rdkit ; extra == 'test'
